picht/__init__.py
picht/core.py
picht/sem.py
picht/test.py
picht-2.2.0.dist-info/licenses/LICENSE
picht-2.2.0.dist-info/METADATA
picht-2.2.0.dist-info/WHEEL
picht-2.2.0.dist-info/top_level.txt
picht-2.2.0.dist-info/RECORD
