Metadata-Version: 2.4
Name: picht
Version: 2.2.0
Summary: Electron optics simulation tool
Home-page: https://github.com/rolypolytoy/picht
Author: Rishiit Sharma
Author-email: Rishiit Sharma <rishiitsharma@gmail.com>
License-Expression: MIT
Project-URL: Homepage, https://github.com/rolypolytoy/picht
Classifier: Programming Language :: Python :: 3
Classifier: Programming Language :: Python :: 3.8
Classifier: Programming Language :: Python :: 3.9
Classifier: Programming Language :: Python :: 3.10
Classifier: Programming Language :: Python :: 3.11
Classifier: Programming Language :: Python :: 3.12
Classifier: Operating System :: OS Independent
Classifier: Topic :: Scientific/Engineering :: Physics
Classifier: Intended Audience :: Science/Research
Classifier: Development Status :: 5 - Production/Stable
Requires-Python: >=3.6
License-File: LICENSE
Requires-Dist: matplotlib
Requires-Dist: scipy
Requires-Dist: numba
Requires-Dist: mendeleev
Requires-Dist: pyamg
Requires-Dist: joblib
Requires-Dist: cadquery
Requires-Dist: h5py
Requires-Dist: numpy==1.26.4
Dynamic: author
Dynamic: home-page
Dynamic: license-file
Dynamic: requires-python
